AUTHORS
ChangeLog
LICENSE
MANIFEST.in
README.rst
setup.cfg
setup.py
ansible/module_utils/dcos.py
ansible/modules/dcos/__init__.py
ansible/modules/dcos/dcos_acl.py
ansible/modules/dcos/dcos_acl_group.py
ansible/modules/dcos/dcos_acl_user.py
ansible/modules/dcos/dcos_group.py
ansible/modules/dcos/dcos_group_member.py
ansible/modules/dcos/dcos_marathon_leader.py
ansible/modules/dcos/dcos_package.py
ansible/modules/dcos/dcos_secret.py
ansible/modules/dcos/dcos_token.py
ansible/modules/dcos/dcos_user.py
ansible/plugins/lookup/dcos_token.py
ansible/plugins/lookup/dcos_token_header.py
ansible_modules_dcos.egg-info/PKG-INFO
ansible_modules_dcos.egg-info/SOURCES.txt
ansible_modules_dcos.egg-info/dependency_links.txt
ansible_modules_dcos.egg-info/requires.txt
ansible_modules_dcos.egg-info/top_level.txt