Metadata-Version: 1.0
Name: ansible-modules-dcos
Version: 1.4.0
Summary: DCOS Ansible Modules
Home-page: https://github.com/TerryHowe/ansible-modules-dcos
Author: Kevin Wood,Terry Howe
Author-email: kevin.wood@example.com
License: MIT
Platform: UNKNOWN
